fenpei/__init__.py
fenpei/combi_sh_single.py
fenpei/job.py
fenpei/job_py.py
fenpei/job_sh.py
fenpei/job_sh_single.py
fenpei/queue.py
fenpei/queue_local.py
fenpei/queue_qsub.py
fenpei/queue_slurm.py
fenpei/sampling.py
fenpei/shell.py
fenpei/substitutions.py
fenpei/utils.py
fenpei-2.4.dist-info/DESCRIPTION.rst
fenpei-2.4.dist-info/METADATA
fenpei-2.4.dist-info/RECORD
fenpei-2.4.dist-info/WHEEL
fenpei-2.4.dist-info/metadata.json
fenpei-2.4.dist-info/top_level.txt
