Metadata-Version: 2.0
Name: fenpei
Version: 2.4
Summary: Distribution of tasks.
Home-page: https://github.com/mverleg/fenpei
Author: (the author)
Author-email: mdilligaf@gmail.com
License: Revised BSD License (LICENSE.txt)
Platform: UNKNOWN
Classifier: Development Status :: 5 - Production/Stable
Classifier: Intended Audience :: Developers
Classifier: Natural Language :: English
Classifier: License :: OSI Approved :: BSD License
Classifier: Operating System :: OS Independent
Classifier: Programming Language :: Python
Classifier: Programming Language :: Python :: 2
Classifier: Programming Language :: Python :: 2.7
Classifier: Programming Language :: Python :: 3
Classifier: Programming Language :: Python :: 3.4
Classifier: Programming Language :: Python :: 3.5
Classifier: Topic :: Software Development :: Libraries :: Python Modules
Requires-Dist: bardeen
Requires-Dist: jinja2
